README.md
setup.py
file_mt_downloader.egg-info/PKG-INFO
file_mt_downloader.egg-info/SOURCES.txt
file_mt_downloader.egg-info/dependency_links.txt
file_mt_downloader.egg-info/requires.txt
file_mt_downloader.egg-info/top_level.txt
src/__init__.py
src/__main__.py
src/file_downloader.py