Metadata-Version: 2.1
Name: file-mt-downloader
Version: 1.0.0
Summary: Python library for file download
Home-page: https://github.com/anexplore/filedownloader.git
Author: anexplore
Maintainer: anexplore
License: Apache-2.0 License
Keywords: file download,downloader
Platform: UNKNOWN
Classifier: Programming Language :: Python :: 3
Classifier: License :: OSI Approved :: Apache Software License
Classifier: Operating System :: OS Independent
Requires-Python: >=3.0, !=3.0.*, !=3.1.*, !=3.2.*, !=3.3.*, !=3.4.*
